README.rst
setup.py
zst.py
zst.egg-info/PKG-INFO
zst.egg-info/SOURCES.txt
zst.egg-info/dependency_links.txt
zst.egg-info/entry_points.txt
zst.egg-info/requires.txt
zst.egg-info/top_level.txt