Metadata-Version: 1.1
Name: zst
Version: 0.1
Summary: Check status of a job in zuul
Home-page: https://github.com/freyes/zst
Author: Felipe Reyes
Author-email: freyes@tty.cl
License: GPLv2+
Keywords: zuul
Platform: UNKNOWN
Classifier: Development Status :: 3 - Alpha
Classifier: Intended Audience :: Developers
Classifier: License :: OSI Approved :: GNU General Public License v2 or later (GPLv2+)
Classifier: Programming Language :: Python :: 3.3
Classifier: Programming Language :: Python :: 3.4
Classifier: Programming Language :: Python :: 3.5
